pl_build/__init__.py
pl_build/backend_linux.py
pl_build/backend_macos.py
pl_build/backend_win32.py
pl_build/core.py
pl_build-1.2.2.dist-info/licenses/LICENSE
pl_build-1.2.2.dist-info/METADATA
pl_build-1.2.2.dist-info/WHEEL
pl_build-1.2.2.dist-info/top_level.txt
pl_build-1.2.2.dist-info/RECORD
